GPatch/GPatch.py
GPatch/__init__.py
GPatch/__main__.py
gpatch-0.4.0.dist-info/LICENSE
gpatch-0.4.0.dist-info/METADATA
gpatch-0.4.0.dist-info/WHEEL
gpatch-0.4.0.dist-info/entry_points.txt
gpatch-0.4.0.dist-info/top_level.txt
gpatch-0.4.0.dist-info/RECORD
