Metadata-Version: 2.1
Name: gpatch
Version: 0.4.0
Summary: Assemble contigs into a chromosome-scalse pseudo-assembly using alignments to a reference sequence. Download the github repository for helper scripts to automate GPatch workflows, identify and correct misjoins in the contig assembly, produce dot-plots of patched pseudoassemblies to a reference assembly, and generate chrom.sizes and liftover chains for patched pseudoassemblies.
Home-page: https://github.com/adadiehl/GPatch
Author: Adam Diehl
Author-email: adadiehl@umich.edu
License: UNKNOWN
Keywords: genomics,genome assembly
Platform: UNKNOWN
Classifier: Development Status :: 4 - Beta
Classifier: Programming Language :: Python :: 3
Classifier: License :: OSI Approved :: MIT License
Classifier: Operating System :: OS Independent
Classifier: Intended Audience :: Science/Research
Classifier: Topic :: Scientific/Engineering
Classifier: Topic :: Scientific/Engineering :: Information Analysis
Classifier: Natural Language :: English
Requires-Dist: Bio
Requires-Dist: pysam
